oimdb/__init__.py
oimdb/core/__init__.py
oimdb/core/all_titles.py
oimdb/core/full_credits.py
oimdb/core/raiting.py
oimdb/core/title.py
oimdb/tests/__init__.py
oimdb/tests/test_all_titles.py
oimdb-0.2.8.dist-info/licenses/LICENSE
oimdb-0.2.8.dist-info/METADATA
oimdb-0.2.8.dist-info/WHEEL
oimdb-0.2.8.dist-info/top_level.txt
oimdb-0.2.8.dist-info/RECORD
