Metadata-Version: 2.4
Name: oimdb
Version: 0.2.8
Summary: Scrape alternative movie titles from IMDb by IMDb ID
Author-email: Anton <dependentgamestudio@gmail.com>
License-Expression: MIT
Requires-Python: >=3.8
License-File: LICENSE
Requires-Dist: playwright>=1.43.0
Requires-Dist: beautifulsoup4>=4.13.4
Requires-Dist: requests>=2.32.3
Requires-Dist: nest-asyncio>=1.6.0
Dynamic: license-file
